rcp/__init__.py
rcp/__main__.py
rcp/main.py
rcp/rcp.py
realclearpolitics-1.4.0.dist-info/METADATA
realclearpolitics-1.4.0.dist-info/WHEEL
realclearpolitics-1.4.0.dist-info/entry_points.txt
realclearpolitics-1.4.0.dist-info/top_level.txt
realclearpolitics-1.4.0.dist-info/RECORD
