Metadata-Version: 1.1
Name: realclearpolitics
Version: 1.4.0
Summary: Python client for RealClearPolitics.
Home-page: https://github.com/AnthonyBloomer/rcp
Author: Anthony Bloomer
Author-email: ant0@protonmail.ch
License: UNKNOWN
Keywords: politics,polls,rcp,realclearpolitics,web scraping
Platform: UNKNOWN
Classifier: License :: OSI Approved :: MIT License
Classifier: Programming Language :: Python :: 2.7
